{
  "results": {
    "dense": [
      {
        "context_tokens": 32607,
        "target_context": 32768,
        "depth": 0.0,
        "needle_idx": 0,
        "mode": "dense",
        "correct": true,
        "expected": "Crimson Falcon",
        "generated": " The secret project codename is Crimson Falcon.\n",
        "trial_idx": 0
      },
      {
        "context_tokens": 32610,
        "target_context": 32768,
        "depth": 0.0,
        "needle_idx": 1,
        "mode": "dense",
        "correct": true,
        "expected": "7429-DELTA",
        "generated": " The secret, code, location, budget, or ID mentioned in the special statement is: 7429-DELTA.\n\n",
        "trial_idx": 1
      },
      {
        "context_tokens": 32607,
        "target_context": 32768,
        "depth": 0.0,
        "needle_idx": 2,
        "mode": "dense",
        "correct": false,
        "expected": "Zurich",
        "generated": " The secret is the history of mathematics. The code is the history of mathematics. The location is the history of mathematics. The budget is the history of mathematics. The ID is the history of mathem",
        "trial_idx": 2
      },
      {
        "context_tokens": 32611,
        "target_context": 32768,
        "depth": 0.0,
        "needle_idx": 3,
        "mode": "dense",
        "correct": false,
        "expected": "4.7 million",
        "generated": " The secret, code, location, budget, or ID mentioned in the special statement is: The history of mathematics spans thousands of years and encompasses many different cultures and civilizations. From th",
        "trial_idx": 3
      },
      {
        "context_tokens": 32610,
        "target_context": 32768,
        "depth": 0.0,
        "needle_idx": 4,
        "mode": "dense",
        "correct": true,
        "expected": "RX-9031",
        "generated": " The secret, code, location, budget, or ID mentioned in the special statement is RX-9031.\n",
        "trial_idx": 4
      },
      {
        "context_tokens": 32611,
        "target_context": 32768,
        "depth": 0.0,
        "needle_idx": 5,
        "mode": "dense",
        "correct": false,
        "expected": "Viper-Seven",
        "generated": " The secret, code, location, budget, or ID mentioned in the special statement is: The history of mathematics spans thousands of years and encompasses many different cultures and civilizations. From th",
        "trial_idx": 5
      },
      {
        "context_tokens": 32610,
        "target_context": 32768,
        "depth": 0.0,
        "needle_idx": 6,
        "mode": "dense",
        "correct": true,
        "expected": "Hotel-Echo-4",
        "generated": " The secret, code, location, budget, or ID mentioned in the special statement is: Hotel-Echo-4.\n",
        "trial_idx": 6
      },
      {
        "context_tokens": 32608,
        "target_context": 32768,
        "depth": 0.0,
        "needle_idx": 7,
        "mode": "dense",
        "correct": false,
        "expected": "47 minutes",
        "generated": " The secret, code, location, budget, or ID mentioned in the special statement is: The history of mathematics spans thousands of years and encompasses many different cultures and civilizations. From th",
        "trial_idx": 7
      },
      {
        "context_tokens": 32611,
        "target_context": 32768,
        "depth": 0.0,
        "needle_idx": 8,
        "mode": "dense",
        "correct": true,
        "expected": "KGB-9982",
        "generated": " The secret, code, location, budget, or ID mentioned in the special statement is: KGB-9982\n",
        "trial_idx": 8
      },
      {
        "context_tokens": 32608,
        "target_context": 32768,
        "depth": 0.0,
        "needle_idx": 9,
        "mode": "dense",
        "correct": false,
        "expected": "Dr. Nakamura",
        "generated": " The secret, code, location, budget, or ID mentioned in the special statement is: The history of mathematics spans thousands of years and encompasses many different cultures and civilizations. From th",
        "trial_idx": 9
      }
    ],
    "certified": [
      {
        "context_tokens": 32607,
        "target_context": 32768,
        "depth": 0.0,
        "needle_idx": 0,
        "mode": "certified",
        "correct": true,
        "expected": "Crimson Falcon",
        "generated": " The secret project codename is Crimson Falcon.\n",
        "ranking_heads_total": 50176,
        "ranking_disagree_r1": 140,
        "ranking_disagree_r3": 437,
        "ranking_fallback_triggered": 581,
        "rung1_fired": true,
        "rung2_fired": true,
        "rung3_fired": true,
        "rung4_fired": false,
        "rung1_fired_layers": 1273,
        "rung2_fired_layers": 1568,
        "rung3_fired_layers": 158,
        "rung4_fired_layers": 0,
        "boundary_check_fired": true,
        "boundary_check_fired_layers": 48,
        "boundary_check_triggered_heads_total": 446,
        "e_key_step_mean": 0.11444528825576322,
        "e_key_step_max": 4.611710071563721,
        "v_max_global": 22.172489166259766,
        "e_val_max": 0.05000000447034836,
        "e_val_mean": 0.02766420091909228,
        "e_val_pre_rung2_max": 0.10637455433607101,
        "e_val_pre_rung2_mean": 0.07448296096860146,
        "value_fallback_blocks": 91255,
        "value_fallback_head_blocks": 608611,
        "tail_mass_int8_est_step_mean": 0.041829245126977256,
        "tail_mass_int8_est_step_max": 0.8493751287460327,
        "k_star_mean": 140.85580755739795,
        "k_star_max": 256,
        "h2d_key_bytes": 0,
        "h2d_value_bytes": 0,
        "h2d_total_bytes": 0,
        "vram_fp16_key_cache_bytes": 104789966848,
        "vram_fp16_value_cache_bytes": 157840048128,
        "fp16_value_cache_hits_step": 0,
        "fp16_value_cache_misses_step": 0,
        "fp16_value_cache_evictions_step": 0,
        "fp16_value_cache_needed_blocks_step": 0,
        "fp16_value_cache_overflow_step": 0,
        "trial_idx": 0
      },
      {
        "context_tokens": 32610,
        "target_context": 32768,
        "depth": 0.0,
        "needle_idx": 1,
        "mode": "certified",
        "correct": true,
        "expected": "7429-DELTA",
        "generated": " The secret, code, location, budget, or ID mentioned in the special statement is: 7429-DELTA.\n\n",
        "ranking_heads_total": 50176,
        "ranking_disagree_r1": 101,
        "ranking_disagree_r3": 432,
        "ranking_fallback_triggered": 580,
        "rung1_fired": true,
        "rung2_fired": true,
        "rung3_fired": true,
        "rung4_fired": false,
        "rung1_fired_layers": 1301,
        "rung2_fired_layers": 1568,
        "rung3_fired_layers": 147,
        "rung4_fired_layers": 0,
        "boundary_check_fired": true,
        "boundary_check_fired_layers": 63,
        "boundary_check_triggered_heads_total": 483,
        "e_key_step_mean": 0.12392542384652783,
        "e_key_step_max": 5.223255157470703,
        "v_max_global": 22.27984046936035,
        "e_val_max": 0.04999999329447746,
        "e_val_mean": 0.024869857477861676,
        "e_val_pre_rung2_max": 0.10444257408380508,
        "e_val_pre_rung2_mean": 0.07581394839537692,
        "value_fallback_blocks": 92304,
        "value_fallback_head_blocks": 611949,
        "tail_mass_int8_est_step_mean": 0.0434339494617865,
        "tail_mass_int8_est_step_max": 0.8495954275131226,
        "k_star_mean": 148.50055803571428,
        "k_star_max": 256,
        "h2d_key_bytes": 0,
        "h2d_value_bytes": 0,
        "h2d_total_bytes": 0,
        "vram_fp16_key_cache_bytes": 104799600640,
        "vram_fp16_value_cache_bytes": 157840048128,
        "fp16_value_cache_hits_step": 0,
        "fp16_value_cache_misses_step": 0,
        "fp16_value_cache_evictions_step": 0,
        "fp16_value_cache_needed_blocks_step": 0,
        "fp16_value_cache_overflow_step": 0,
        "trial_idx": 1
      },
      {
        "context_tokens": 32607,
        "target_context": 32768,
        "depth": 0.0,
        "needle_idx": 2,
        "mode": "certified",
        "correct": false,
        "expected": "Zurich",
        "generated": " The secret is the history of mathematics. The code is the history of mathematics. The location is the history of mathematics. The budget is the history of mathematics. The ID is the history of mathem",
        "ranking_heads_total": 50176,
        "ranking_disagree_r1": 63,
        "ranking_disagree_r3": 519,
        "ranking_fallback_triggered": 563,
        "rung1_fired": true,
        "rung2_fired": true,
        "rung3_fired": true,
        "rung4_fired": false,
        "rung1_fired_layers": 1535,
        "rung2_fired_layers": 1568,
        "rung3_fired_layers": 141,
        "rung4_fired_layers": 0,
        "boundary_check_fired": true,
        "boundary_check_fired_layers": 90,
        "boundary_check_triggered_heads_total": 503,
        "e_key_step_mean": 0.19859833852150383,
        "e_key_step_max": 6.568522930145264,
        "v_max_global": 22.217893600463867,
        "e_val_max": 0.04999995231628418,
        "e_val_mean": 0.02237049492722857,
        "e_val_pre_rung2_max": 0.10147982090711594,
        "e_val_pre_rung2_mean": 0.07631798344664276,
        "value_fallback_blocks": 98886,
        "value_fallback_head_blocks": 628539,
        "tail_mass_int8_est_step_mean": 0.05546433280450197,
        "tail_mass_int8_est_step_max": 0.8495630621910095,
        "k_star_mean": 176.75655691964286,
        "k_star_max": 256,
        "h2d_key_bytes": 0,
        "h2d_value_bytes": 0,
        "h2d_total_bytes": 0,
        "vram_fp16_key_cache_bytes": 104789966848,
        "vram_fp16_value_cache_bytes": 157840048128,
        "fp16_value_cache_hits_step": 0,
        "fp16_value_cache_misses_step": 0,
        "fp16_value_cache_evictions_step": 0,
        "fp16_value_cache_needed_blocks_step": 0,
        "fp16_value_cache_overflow_step": 0,
        "trial_idx": 2
      },
      {
        "context_tokens": 32611,
        "target_context": 32768,
        "depth": 0.0,
        "needle_idx": 3,
        "mode": "certified",
        "correct": false,
        "expected": "4.7 million",
        "generated": " The secret, code, location, budget, or ID mentioned in the special statement is: The history of mathematics spans thousands of years and encompasses many different cultures and civilizations. From th",
        "ranking_heads_total": 50176,
        "ranking_disagree_r1": 69,
        "ranking_disagree_r3": 579,
        "ranking_fallback_triggered": 187,
        "rung1_fired": true,
        "rung2_fired": true,
        "rung3_fired": true,
        "rung4_fired": false,
        "rung1_fired_layers": 1554,
        "rung2_fired_layers": 1568,
        "rung3_fired_layers": 145,
        "rung4_fired_layers": 0,
        "boundary_check_fired": true,
        "boundary_check_fired_layers": 82,
        "boundary_check_triggered_heads_total": 121,
        "e_key_step_mean": 0.23528829028435547,
        "e_key_step_max": 7.156928539276123,
        "v_max_global": 22.270769119262695,
        "e_val_max": 0.04999988153576851,
        "e_val_mean": 0.02273458654339525,
        "e_val_pre_rung2_max": 0.10376933962106705,
        "e_val_pre_rung2_mean": 0.07671476637811533,
        "value_fallback_blocks": 58330,
        "value_fallback_head_blocks": 208118,
        "tail_mass_int8_est_step_mean": 0.04678583173770268,
        "tail_mass_int8_est_step_max": 0.7583514451980591,
        "k_star_mean": 187.84516501913265,
        "k_star_max": 256,
        "h2d_key_bytes": 0,
        "h2d_value_bytes": 0,
        "h2d_total_bytes": 0,
        "vram_fp16_key_cache_bytes": 104802811904,
        "vram_fp16_value_cache_bytes": 157840048128,
        "fp16_value_cache_hits_step": 0,
        "fp16_value_cache_misses_step": 0,
        "fp16_value_cache_evictions_step": 0,
        "fp16_value_cache_needed_blocks_step": 0,
        "fp16_value_cache_overflow_step": 0,
        "trial_idx": 3
      },
      {
        "context_tokens": 32610,
        "target_context": 32768,
        "depth": 0.0,
        "needle_idx": 4,
        "mode": "certified",
        "correct": true,
        "expected": "RX-9031",
        "generated": " The secret, code, location, budget, or ID mentioned in the special statement is RX-9031.\n",
        "ranking_heads_total": 50176,
        "ranking_disagree_r1": 83,
        "ranking_disagree_r3": 426,
        "ranking_fallback_triggered": 552,
        "rung1_fired": true,
        "rung2_fired": true,
        "rung3_fired": true,
        "rung4_fired": false,
        "rung1_fired_layers": 1282,
        "rung2_fired_layers": 1568,
        "rung3_fired_layers": 129,
        "rung4_fired_layers": 0,
        "boundary_check_fired": true,
        "boundary_check_fired_layers": 63,
        "boundary_check_triggered_heads_total": 473,
        "e_key_step_mean": 0.120382229342572,
        "e_key_step_max": 5.624527931213379,
        "v_max_global": 22.362234115600586,
        "e_val_max": 0.04999992251396179,
        "e_val_mean": 0.024397521160812622,
        "e_val_pre_rung2_max": 0.10337960720062256,
        "e_val_pre_rung2_mean": 0.07569772137652095,
        "value_fallback_blocks": 91708,
        "value_fallback_head_blocks": 610303,
        "tail_mass_int8_est_step_mean": 0.04268885525870042,
        "tail_mass_int8_est_step_max": 0.8497083783149719,
        "k_star_mean": 145.8261120854592,
        "k_star_max": 256,
        "h2d_key_bytes": 0,
        "h2d_value_bytes": 0,
        "h2d_total_bytes": 0,
        "vram_fp16_key_cache_bytes": 104799600640,
        "vram_fp16_value_cache_bytes": 157840048128,
        "fp16_value_cache_hits_step": 0,
        "fp16_value_cache_misses_step": 0,
        "fp16_value_cache_evictions_step": 0,
        "fp16_value_cache_needed_blocks_step": 0,
        "fp16_value_cache_overflow_step": 0,
        "trial_idx": 4
      },
      {
        "context_tokens": 32611,
        "target_context": 32768,
        "depth": 0.0,
        "needle_idx": 5,
        "mode": "certified",
        "correct": false,
        "expected": "Viper-Seven",
        "generated": " The secret, code, location, budget, or ID mentioned in the special statement is: The history of mathematics spans thousands of years and encompasses many different cultures and civilizations. From th",
        "ranking_heads_total": 50176,
        "ranking_disagree_r1": 38,
        "ranking_disagree_r3": 516,
        "ranking_fallback_triggered": 176,
        "rung1_fired": true,
        "rung2_fired": true,
        "rung3_fired": true,
        "rung4_fired": false,
        "rung1_fired_layers": 1557,
        "rung2_fired_layers": 1568,
        "rung3_fired_layers": 126,
        "rung4_fired_layers": 0,
        "boundary_check_fired": true,
        "boundary_check_fired_layers": 94,
        "boundary_check_triggered_heads_total": 141,
        "e_key_step_mean": 0.24515639635026265,
        "e_key_step_max": 7.458587646484375,
        "v_max_global": 22.12965965270996,
        "e_val_max": 0.049999866634607315,
        "e_val_mean": 0.02277828395255005,
        "e_val_pre_rung2_max": 0.10420210659503937,
        "e_val_pre_rung2_mean": 0.07694721707542028,
        "value_fallback_blocks": 58666,
        "value_fallback_head_blocks": 208964,
        "tail_mass_int8_est_step_mean": 0.04712405320903172,
        "tail_mass_int8_est_step_max": 0.758426308631897,
        "k_star_mean": 188.5266661352041,
        "k_star_max": 256,
        "h2d_key_bytes": 0,
        "h2d_value_bytes": 0,
        "h2d_total_bytes": 0,
        "vram_fp16_key_cache_bytes": 104802811904,
        "vram_fp16_value_cache_bytes": 157840048128,
        "fp16_value_cache_hits_step": 0,
        "fp16_value_cache_misses_step": 0,
        "fp16_value_cache_evictions_step": 0,
        "fp16_value_cache_needed_blocks_step": 0,
        "fp16_value_cache_overflow_step": 0,
        "trial_idx": 5
      },
      {
        "context_tokens": 32610,
        "target_context": 32768,
        "depth": 0.0,
        "needle_idx": 6,
        "mode": "certified",
        "correct": true,
        "expected": "Hotel-Echo-4",
        "generated": " The secret, code, location, budget, or ID mentioned in the special statement is: Hotel-Echo-4.\n",
        "ranking_heads_total": 50176,
        "ranking_disagree_r1": 92,
        "ranking_disagree_r3": 463,
        "ranking_fallback_triggered": 583,
        "rung1_fired": true,
        "rung2_fired": true,
        "rung3_fired": true,
        "rung4_fired": false,
        "rung1_fired_layers": 1364,
        "rung2_fired_layers": 1568,
        "rung3_fired_layers": 147,
        "rung4_fired_layers": 0,
        "boundary_check_fired": true,
        "boundary_check_fired_layers": 71,
        "boundary_check_triggered_heads_total": 494,
        "e_key_step_mean": 0.13334117331530196,
        "e_key_step_max": 5.924281597137451,
        "v_max_global": 22.451961517333984,
        "e_val_max": 0.04999995976686478,
        "e_val_mean": 0.02550036858349126,
        "e_val_pre_rung2_max": 0.10372423380613327,
        "e_val_pre_rung2_mean": 0.07583322832170798,
        "value_fallback_blocks": 93324,
        "value_fallback_head_blocks": 613164,
        "tail_mass_int8_est_step_mean": 0.04513373800044956,
        "tail_mass_int8_est_step_max": 0.8497306704521179,
        "k_star_mean": 154.32860331632654,
        "k_star_max": 256,
        "h2d_key_bytes": 0,
        "h2d_value_bytes": 0,
        "h2d_total_bytes": 0,
        "vram_fp16_key_cache_bytes": 104799600640,
        "vram_fp16_value_cache_bytes": 157840048128,
        "fp16_value_cache_hits_step": 0,
        "fp16_value_cache_misses_step": 0,
        "fp16_value_cache_evictions_step": 0,
        "fp16_value_cache_needed_blocks_step": 0,
        "fp16_value_cache_overflow_step": 0,
        "trial_idx": 6
      },
      {
        "context_tokens": 32608,
        "target_context": 32768,
        "depth": 0.0,
        "needle_idx": 7,
        "mode": "certified",
        "correct": false,
        "expected": "47 minutes",
        "generated": " The secret, code, location, budget, or ID mentioned in the special statement is: The history of mathematics spans thousands of years and encompasses many different cultures and civilizations. From th",
        "ranking_heads_total": 50176,
        "ranking_disagree_r1": 54,
        "ranking_disagree_r3": 569,
        "ranking_fallback_triggered": 191,
        "rung1_fired": true,
        "rung2_fired": true,
        "rung3_fired": true,
        "rung4_fired": false,
        "rung1_fired_layers": 1550,
        "rung2_fired_layers": 1568,
        "rung3_fired_layers": 136,
        "rung4_fired_layers": 0,
        "boundary_check_fired": true,
        "boundary_check_fired_layers": 93,
        "boundary_check_triggered_heads_total": 138,
        "e_key_step_mean": 0.23413207984472417,
        "e_key_step_max": 6.941157341003418,
        "v_max_global": 22.457212448120117,
        "e_val_max": 0.04999976605176926,
        "e_val_mean": 0.02288739596807151,
        "e_val_pre_rung2_max": 0.10270839184522629,
        "e_val_pre_rung2_mean": 0.07689373325841616,
        "value_fallback_blocks": 59135,
        "value_fallback_head_blocks": 209793,
        "tail_mass_int8_est_step_mean": 0.0472182418987136,
        "tail_mass_int8_est_step_max": 0.7604699730873108,
        "k_star_mean": 186.94088807397958,
        "k_star_max": 256,
        "h2d_key_bytes": 0,
        "h2d_value_bytes": 0,
        "h2d_total_bytes": 0,
        "vram_fp16_key_cache_bytes": 104793178112,
        "vram_fp16_value_cache_bytes": 157840048128,
        "fp16_value_cache_hits_step": 0,
        "fp16_value_cache_misses_step": 0,
        "fp16_value_cache_evictions_step": 0,
        "fp16_value_cache_needed_blocks_step": 0,
        "fp16_value_cache_overflow_step": 0,
        "trial_idx": 7
      },
      {
        "context_tokens": 32611,
        "target_context": 32768,
        "depth": 0.0,
        "needle_idx": 8,
        "mode": "certified",
        "correct": true,
        "expected": "KGB-9982",
        "generated": " The secret, code, location, budget, or ID mentioned in the special statement is: KGB-9982.\n",
        "ranking_heads_total": 50176,
        "ranking_disagree_r1": 115,
        "ranking_disagree_r3": 467,
        "ranking_fallback_triggered": 601,
        "rung1_fired": true,
        "rung2_fired": true,
        "rung3_fired": true,
        "rung4_fired": false,
        "rung1_fired_layers": 1431,
        "rung2_fired_layers": 1568,
        "rung3_fired_layers": 167,
        "rung4_fired_layers": 0,
        "boundary_check_fired": true,
        "boundary_check_fired_layers": 75,
        "boundary_check_triggered_heads_total": 492,
        "e_key_step_mean": 0.136041691266618,
        "e_key_step_max": 5.964268207550049,
        "v_max_global": 22.193435668945312,
        "e_val_max": 0.04999994486570358,
        "e_val_mean": 0.02573223209898914,
        "e_val_pre_rung2_max": 0.10440027713775635,
        "e_val_pre_rung2_mean": 0.07542733756863342,
        "value_fallback_blocks": 93353,
        "value_fallback_head_blocks": 610213,
        "tail_mass_int8_est_step_mean": 0.04482948556732463,
        "tail_mass_int8_est_step_max": 0.849746823310852,
        "k_star_mean": 161.60690369897958,
        "k_star_max": 256,
        "h2d_key_bytes": 0,
        "h2d_value_bytes": 0,
        "h2d_total_bytes": 0,
        "vram_fp16_key_cache_bytes": 104802811904,
        "vram_fp16_value_cache_bytes": 157840048128,
        "fp16_value_cache_hits_step": 0,
        "fp16_value_cache_misses_step": 0,
        "fp16_value_cache_evictions_step": 0,
        "fp16_value_cache_needed_blocks_step": 0,
        "fp16_value_cache_overflow_step": 0,
        "trial_idx": 8
      },
      {
        "context_tokens": 32608,
        "target_context": 32768,
        "depth": 0.0,
        "needle_idx": 9,
        "mode": "certified",
        "correct": false,
        "expected": "Dr. Nakamura",
        "generated": " The secret, code, location, budget, or ID mentioned in the special statement is: The history of mathematics spans thousands of years and encompasses many different cultures and civilizations. From th",
        "ranking_heads_total": 50176,
        "ranking_disagree_r1": 56,
        "ranking_disagree_r3": 575,
        "ranking_fallback_triggered": 184,
        "rung1_fired": true,
        "rung2_fired": true,
        "rung3_fired": true,
        "rung4_fired": false,
        "rung1_fired_layers": 1552,
        "rung2_fired_layers": 1568,
        "rung3_fired_layers": 136,
        "rung4_fired_layers": 0,
        "boundary_check_fired": true,
        "boundary_check_fired_layers": 91,
        "boundary_check_triggered_heads_total": 131,
        "e_key_step_mean": 0.2409741658983486,
        "e_key_step_max": 6.931056976318359,
        "v_max_global": 23.109037399291992,
        "e_val_max": 0.049999985843896866,
        "e_val_mean": 0.02287141552503216,
        "e_val_pre_rung2_max": 0.10550832748413086,
        "e_val_pre_rung2_mean": 0.07688961303507795,
        "value_fallback_blocks": 59059,
        "value_fallback_head_blocks": 209675,
        "tail_mass_int8_est_step_mean": 0.047340748513269484,
        "tail_mass_int8_est_step_max": 0.7604669332504272,
        "k_star_mean": 188.09060108418367,
        "k_star_max": 256,
        "h2d_key_bytes": 0,
        "h2d_value_bytes": 0,
        "h2d_total_bytes": 0,
        "vram_fp16_key_cache_bytes": 104793178112,
        "vram_fp16_value_cache_bytes": 157840048128,
        "fp16_value_cache_hits_step": 0,
        "fp16_value_cache_misses_step": 0,
        "fp16_value_cache_evictions_step": 0,
        "fp16_value_cache_needed_blocks_step": 0,
        "fp16_value_cache_overflow_step": 0,
        "trial_idx": 9
      }
    ]
  },
  "heatmaps": {
    "dense": {
      "32K_d0.0": 0.5
    },
    "certified": {
      "32K_d0.0": 0.5
    }
  },
  "dense_accuracy": 0.5,
  "certified_accuracy": 0.5,
  "critical_failures": 0,
  "paired_stats": {
    "n": 10,
    "dense_correct": 5,
    "certified_correct": 5,
    "dense_accuracy": 0.5,
    "certified_accuracy": 0.5,
    "delta_accuracy": 0.0,
    "delta_pp": 0.0,
    "bootstrap_ci_lo": 0.0,
    "bootstrap_ci_hi": 0.0,
    "bootstrap_ci_pp_lo": 0.0,
    "bootstrap_ci_pp_hi": 0.0,
    "bootstrap_iters": 10000,
    "bootstrap_seed": 20260425,
    "mcnemar_p": 1.0,
    "mcnemar": {
      "test": "exact_two_sided_binomial",
      "p_value": 1.0,
      "discordant": 0,
      "dense_only": 0,
      "certified_only": 0
    },
    "paired_table": {
      "both_correct": 5,
      "dense_only": 0,
      "certified_only": 0,
      "both_wrong": 5
    }
  },
  "paired_stats_by_context": {
    "32K": {
      "n": 10,
      "dense_correct": 5,
      "certified_correct": 5,
      "dense_accuracy": 0.5,
      "certified_accuracy": 0.5,
      "delta_accuracy": 0.0,
      "delta_pp": 0.0,
      "bootstrap_ci_lo": 0.0,
      "bootstrap_ci_hi": 0.0,
      "bootstrap_ci_pp_lo": 0.0,
      "bootstrap_ci_pp_hi": 0.0,
      "bootstrap_iters": 10000,
      "bootstrap_seed": 20260425,
      "mcnemar_p": 1.0,
      "mcnemar": {
        "test": "exact_two_sided_binomial",
        "p_value": 1.0,
        "discordant": 0,
        "dense_only": 0,
        "certified_only": 0
      },
      "paired_table": {
        "both_correct": 5,
        "dense_only": 0,
        "certified_only": 0,
        "both_wrong": 5
      }
    }
  },
  "paired_stats_by_needle_group": {
    "original": {
      "n": 5,
      "dense_correct": 3,
      "certified_correct": 3,
      "dense_accuracy": 0.6,
      "certified_accuracy": 0.6,
      "delta_accuracy": 0.0,
      "delta_pp": 0.0,
      "bootstrap_ci_lo": 0.0,
      "bootstrap_ci_hi": 0.0,
      "bootstrap_ci_pp_lo": 0.0,
      "bootstrap_ci_pp_hi": 0.0,
      "bootstrap_iters": 10000,
      "bootstrap_seed": 20260425,
      "mcnemar_p": 1.0,
      "mcnemar": {
        "test": "exact_two_sided_binomial",
        "p_value": 1.0,
        "discordant": 0,
        "dense_only": 0,
        "certified_only": 0
      },
      "paired_table": {
        "both_correct": 3,
        "dense_only": 0,
        "certified_only": 0,
        "both_wrong": 2
      }
    },
    "harder": {
      "n": 5,
      "dense_correct": 2,
      "certified_correct": 2,
      "dense_accuracy": 0.4,
      "certified_accuracy": 0.4,
      "delta_accuracy": 0.0,
      "delta_pp": 0.0,
      "bootstrap_ci_lo": 0.0,
      "bootstrap_ci_hi": 0.0,
      "bootstrap_ci_pp_lo": 0.0,
      "bootstrap_ci_pp_hi": 0.0,
      "bootstrap_iters": 10000,
      "bootstrap_seed": 20260426,
      "mcnemar_p": 1.0,
      "mcnemar": {
        "test": "exact_two_sided_binomial",
        "p_value": 1.0,
        "discordant": 0,
        "dense_only": 0,
        "certified_only": 0
      },
      "paired_table": {
        "both_correct": 2,
        "dense_only": 0,
        "certified_only": 0,
        "both_wrong": 3
      }
    }
  },
  "cache_config": {
    "v_tolerance": 0.05,
    "quantization_mode": "asymmetric_int8_keys+int4_g16_values",
    "asymmetric_keys": true,
    "use_int4_values": true,
    "group_size": 16,
    "score_consistency_check": false,
    "tau_cov": 0.995,
    "k_min": 2,
    "k_max": 128,
    "ranking_fallback": true,
    "ranking_r": 1,
    "ranking_fallback_mode": "full",
    "fp16_key_cache_blocks": 3072,
    "fp16_value_cache_blocks": 3072,
    "eps_guard": 0.01,
    "exploration_rate": 0.02,
    "rung1_threshold": 0.02,
    "rung1_multiplier": 2.0,
    "attention_backend": "native_blackwell",
    "static_resident_cache": "1",
    "splitk_blocks_per_split": "auto_native_32_24_16",
    "cuda_graph_decode": false,
    "runtime_profile": "0",
    "code_sha": "d10d55b2c2f08d519a097a3889c21a2c3d92e691-dirty",
    "dotcache_config_hash": "231a174f8ccccc3464543e3c86c846f33f61ffbe5a84b9026184f0d0365a1715"
  },
  "ranking_fallback_summary": {
    "mode": "full",
    "r": 1,
    "heads_total": 501760,
    "disagree_r1": 811,
    "disagree_r3": 4983,
    "triggered": 4198,
    "disagree_rate_r1": 0.001616310586734694,
    "disagree_rate_r3": 0.009931042729591836,
    "fallback_rate": 0.008366549744897958
  }
}