{
  "benchmark": "ruler_subset",
  "model": "NousResearch/Meta-Llama-3.1-8B",
  "subtasks": [
    "niah_single",
    "niah_multikey",
    "niah_multivalue",
    "niah_multiquery",
    "vt",
    "cwe",
    "fwe"
  ],
  "contexts": [
    65536
  ],
  "num_samples": 1,
  "sample_start": 7,
  "top_k_fp16": 4,
  "seed": 20260416,
  "wall_minutes": 6.25140967296611,
  "overall_dense": 0.7976190476190476,
  "overall_cert": 0.869047619047619,
  "critical_failures": 0,
  "paired_stats": {
    "n": 7,
    "dense_mean": 0.7976190476190476,
    "certified_mean": 0.869047619047619,
    "delta": 0.07142857142857142,
    "delta_ci_lo": 0.0,
    "delta_ci_hi": 0.21428571428571427,
    "bootstrap_iters": 10000,
    "bootstrap_seed": 20260425
  },
  "paired_stats_by_context": {
    "64K": {
      "n": 7,
      "dense_mean": 0.7976190476190476,
      "certified_mean": 0.869047619047619,
      "delta": 0.07142857142857142,
      "delta_ci_lo": 0.0,
      "delta_ci_hi": 0.21428571428571427,
      "bootstrap_iters": 10000,
      "bootstrap_seed": 20260425
    }
  },
  "paired_stats_by_task_context": {
    "cwe_64K": {
      "n": 1,
      "dense_mean": 1.0,
      "certified_mean": 1.0,
      "delta": 0.0,
      "delta_ci_lo": 0.0,
      "delta_ci_hi": 0.0,
      "bootstrap_iters": 10000,
      "bootstrap_seed": 20260425
    },
    "fwe_64K": {
      "n": 1,
      "dense_mean": 0.3333333333333333,
      "certified_mean": 0.3333333333333333,
      "delta": 0.0,
      "delta_ci_lo": 0.0,
      "delta_ci_hi": 0.0,
      "bootstrap_iters": 10000,
      "bootstrap_seed": 20260426
    },
    "niah_multikey_64K": {
      "n": 1,
      "dense_mean": 1.0,
      "certified_mean": 1.0,
      "delta": 0.0,
      "delta_ci_lo": 0.0,
      "delta_ci_hi": 0.0,
      "bootstrap_iters": 10000,
      "bootstrap_seed": 20260427
    },
    "niah_multiquery_64K": {
      "n": 1,
      "dense_mean": 1.0,
      "certified_mean": 1.0,
      "delta": 0.0,
      "delta_ci_lo": 0.0,
      "delta_ci_hi": 0.0,
      "bootstrap_iters": 10000,
      "bootstrap_seed": 20260428
    },
    "niah_multivalue_64K": {
      "n": 1,
      "dense_mean": 1.0,
      "certified_mean": 1.0,
      "delta": 0.0,
      "delta_ci_lo": 0.0,
      "delta_ci_hi": 0.0,
      "bootstrap_iters": 10000,
      "bootstrap_seed": 20260429
    },
    "niah_single_64K": {
      "n": 1,
      "dense_mean": 1.0,
      "certified_mean": 1.0,
      "delta": 0.0,
      "delta_ci_lo": 0.0,
      "delta_ci_hi": 0.0,
      "bootstrap_iters": 10000,
      "bootstrap_seed": 20260430
    },
    "vt_64K": {
      "n": 1,
      "dense_mean": 0.25,
      "certified_mean": 0.75,
      "delta": 0.5,
      "delta_ci_lo": 0.5,
      "delta_ci_hi": 0.5,
      "bootstrap_iters": 10000,
      "bootstrap_seed": 20260431
    }
  },
  "summary": {
    "niah_single_64K": {
      "dense_mean": 1.0,
      "cert_mean": 1.0,
      "critical": 0,
      "n": 1
    },
    "niah_multikey_64K": {
      "dense_mean": 1.0,
      "cert_mean": 1.0,
      "critical": 0,
      "n": 1
    },
    "niah_multivalue_64K": {
      "dense_mean": 1.0,
      "cert_mean": 1.0,
      "critical": 0,
      "n": 1
    },
    "niah_multiquery_64K": {
      "dense_mean": 1.0,
      "cert_mean": 1.0,
      "critical": 0,
      "n": 1
    },
    "vt_64K": {
      "dense_mean": 0.25,
      "cert_mean": 0.75,
      "critical": 0,
      "n": 1
    },
    "cwe_64K": {
      "dense_mean": 1.0,
      "cert_mean": 1.0,
      "critical": 0,
      "n": 1
    },
    "fwe_64K": {
      "dense_mean": 0.3333333333333333,
      "cert_mean": 0.3333333333333333,
      "critical": 0,
      "n": 1
    }
  },
  "results": [
    {
      "subtask": "niah_single",
      "ctx_tokens": 65536,
      "sample_idx": 7,
      "seq_len": 65374,
      "refs": [
        "6264919"
      ],
      "dense_score": 1.0,
      "dense_gen": " 6264919.\n\nWhat is the special magic number for quarry mentioned in the provided text?\nThe special magic number for quarry mentioned in the provided text is ",
      "cert_score": 1.0,
      "cert_gen": " 6264919.\n\nWhat is the special magic number for quarry mentioned in the provided text?\nThe special magic number for quarry mentioned in the provided text is ",
      "critical": false,
      "cert_stats": {
        "skip_rate": 0.9332477511655736,
        "total_blocks": 129748992,
        "skipped_blocks": 121087955,
        "per_layer_skip_rate": {
          "0": 0.9183203889432485,
          "1": 0.9275088674168297,
          "2": 0.9593627690802349,
          "3": 0.9518407534246576,
          "4": 0.9574516878669276,
          "5": 0.95092343444227,
          "6": 0.9327222969667319,
          "7": 0.9407182607632094,
          "8": 0.9374847113502935,
          "9": 0.9234955968688845,
          "10": 0.9384631849315068,
          "11": 0.9200556506849316,
          "12": 0.9246881115459883,
          "13": 0.9275623776908023,
          "14": 0.9265991927592955,
          "15": 0.9350461717221135,
          "16": 0.9400226272015656,
          "17": 0.9283650318003914,
          "18": 0.9246881115459883,
          "19": 0.9315374266144814,
          "20": 0.9301614481409002,
          "21": 0.9343734711350293,
          "22": 0.9209806139921722,
          "23": 0.925880626223092,
          "24": 0.9303984222113503,
          "25": 0.9413374510763209,
          "26": 0.92481042074364,
          "27": 0.9257659613502935,
          "28": 0.9268208781800391,
          "29": 0.9348397749510763,
          "30": 0.9259035591976517,
          "31": 0.9337237035225049
        },
        "ranking_heads_total": 31744,
        "ranking_disagree_r1": 45,
        "ranking_disagree_r3": 397,
        "ranking_fallback_triggered": 144,
        "ranking_disagree_rate_r1": 0.0014175907258064517,
        "ranking_disagree_rate_r3": 0.012506300403225807,
        "ranking_fallback_rate": 0.0045362903225806455,
        "exploration_blocks_total": 2473805,
        "h2d_key_bytes": 0,
        "h2d_value_bytes": 0,
        "h2d_total_bytes": 0,
        "h2d_key_blocks": 0,
        "h2d_value_blocks": 0,
        "vram_fp16_key_cache_bytes": 132847370240,
        "vram_fp16_value_cache_bytes": 166429982720,
        "fp16_value_cache_hits_step": 0,
        "fp16_value_cache_misses_step": 0,
        "fp16_value_cache_evictions_step": 0,
        "fp16_value_cache_needed_blocks_step": 0,
        "fp16_value_cache_overflow_step": 0,
        "rung1_fired": true,
        "rung1_fired_layers": 992,
        "rung2_fired": true,
        "rung2_fired_layers": 992,
        "rung3_fired": true,
        "rung3_fired_layers": 88,
        "rung4_fired": false,
        "rung4_fired_layers": 0,
        "boundary_check_fired": true,
        "boundary_check_fired_layers": 54,
        "boundary_check_triggered_heads_total": 100,
        "fp16_cache_capacity_blocks": 5120,
        "fp16_cache_hits": 0,
        "fp16_cache_misses": 0,
        "fp16_cache_evictions": 0,
        "fp16_cache_resident_blocks_sum": 4056288,
        "fp16_cache_hit_rate": 0.0,
        "k_star_mean": 193.97479838709677,
        "k_star_max": 256,
        "tail_mass_int8_est_step_mean": 0.04651658092400119,
        "tail_mass_int8_est_step_max": 0.8614574074745178,
        "e_key_step_mean": 0.22239742690749886,
        "e_key_step_max": 6.044278621673584,
        "e_val_mean": 0.024386741760780192,
        "e_val_max": 0.04999995976686478,
        "e_val_pre_rung2_mean": 0.0761801086200942,
        "e_val_pre_rung2_max": 0.10329241305589676,
        "value_fallback_blocks": 47054,
        "value_fallback_head_blocks": 166391,
        "v_max_global": 22.195491790771484
      }
    },
    {
      "subtask": "niah_multikey",
      "ctx_tokens": 65536,
      "sample_idx": 7,
      "seq_len": 65423,
      "refs": [
        "8772069"
      ],
      "dense_score": 1.0,
      "dense_gen": ": 8772069.\n\nWhat is the special magic number for ember mentioned in the provided text?\nThe special magic number for ember mentioned in the provided text is",
      "cert_score": 1.0,
      "cert_gen": ": 8772069.\n\nWhat is the special magic number for ember mentioned in the provided text?\nThe special magic number for ember mentioned in the provided text is",
      "critical": false,
      "cert_stats": {
        "skip_rate": 0.9342091084447923,
        "total_blocks": 129846272,
        "skipped_blocks": 121303570,
        "per_layer_skip_rate": {
          "0": 0.9179525177218284,
          "1": 0.9248808359814227,
          "2": 0.951562881935957,
          "3": 0.9556343192373503,
          "4": 0.9439852725494989,
          "5": 0.9442908213150819,
          "6": 0.9382638719139574,
          "7": 0.9388902468834026,
          "8": 0.9277911879736006,
          "9": 0.9205573209484234,
          "10": 0.9331764849670008,
          "11": 0.9274856392080176,
          "12": 0.9360868369591787,
          "13": 0.9287994989000244,
          "14": 0.9285779760449768,
          "15": 0.9474990833537033,
          "16": 0.9404103519921779,
          "17": 0.9332375947201174,
          "18": 0.942617941823515,
          "19": 0.939745783427035,
          "20": 0.9342917379613787,
          "21": 0.9440234661451967,
          "22": 0.9369652896602297,
          "23": 0.9427325226106087,
          "24": 0.9401124419457345,
          "25": 0.9501344414568565,
          "26": 0.9289217184062576,
          "27": 0.9378208262038621,
          "28": 0.933512588609142,
          "29": 0.9395853703251039,
          "30": 0.9277071620630652,
          "31": 0.9359646174529455
        },
        "ranking_heads_total": 31744,
        "ranking_disagree_r1": 42,
        "ranking_disagree_r3": 369,
        "ranking_fallback_triggered": 157,
        "ranking_disagree_rate_r1": 0.0013230846774193547,
        "ranking_disagree_rate_r3": 0.011624243951612902,
        "ranking_fallback_rate": 0.0049458165322580645,
        "exploration_blocks_total": 2476914,
        "h2d_key_bytes": 0,
        "h2d_value_bytes": 0,
        "h2d_total_bytes": 0,
        "h2d_key_blocks": 0,
        "h2d_value_blocks": 0,
        "vram_fp16_key_cache_bytes": 132946919424,
        "vram_fp16_value_cache_bytes": 166429982720,
        "fp16_value_cache_hits_step": 0,
        "fp16_value_cache_misses_step": 0,
        "fp16_value_cache_evictions_step": 0,
        "fp16_value_cache_needed_blocks_step": 0,
        "fp16_value_cache_overflow_step": 0,
        "rung1_fired": true,
        "rung1_fired_layers": 991,
        "rung2_fired": true,
        "rung2_fired_layers": 992,
        "rung3_fired": true,
        "rung3_fired_layers": 98,
        "rung4_fired": false,
        "rung4_fired_layers": 0,
        "boundary_check_fired": true,
        "boundary_check_fired_layers": 62,
        "boundary_check_triggered_heads_total": 115,
        "fp16_cache_capacity_blocks": 5120,
        "fp16_cache_hits": 0,
        "fp16_cache_misses": 0,
        "fp16_cache_evictions": 0,
        "fp16_cache_resident_blocks_sum": 4059264,
        "fp16_cache_hit_rate": 0.0,
        "k_star_mean": 190.1490675403226,
        "k_star_max": 256,
        "tail_mass_int8_est_step_mean": 0.04673911177087575,
        "tail_mass_int8_est_step_max": 0.8622293472290039,
        "e_key_step_mean": 0.2245169852713814,
        "e_key_step_max": 5.045371055603027,
        "e_val_mean": 0.023104511899404198,
        "e_val_max": 0.049999967217445374,
        "e_val_pre_rung2_mean": 0.07613963641286377,
        "e_val_pre_rung2_max": 0.10161328315734863,
        "value_fallback_blocks": 47873,
        "value_fallback_head_blocks": 167836,
        "v_max_global": 22.101469039916992
      }
    },
    {
      "subtask": "niah_multivalue",
      "ctx_tokens": 65536,
      "sample_idx": 7,
      "seq_len": 65420,
      "refs": [
        "1575176",
        "6503915",
        "2535910",
        "1378989"
      ],
      "dense_score": 1.0,
      "dense_gen": ": 1575176, 6503915, 2535910, 1378989, 1378989, 1378989, 1378989, 1378989, 1378989, 1378989, 1378989, 1378989, 1378989, 1378989, 1378989, 1378989, 1378989, 1378989, 1378989,",
      "cert_score": 1.0,
      "cert_gen": ": 1575176, 6503915, 2535910, 1378989, 1378989, 1378989, 1378989, 1378989, 1378989, 1378989, 1378989, 1378989, 1378989, 1378989, 1378989, 1378989, 1378989, 1378989, 1378989,",
      "critical": false,
      "cert_stats": {
        "skip_rate": 0.9393434139765499,
        "total_blocks": 398091264,
        "skipped_blocks": 373944407,
        "per_layer_skip_rate": {
          "0": 0.9182539682539682,
          "1": 0.9242063492063493,
          "2": 0.9492216117216117,
          "3": 0.9362179487179487,
          "4": 0.943986568986569,
          "5": 0.9370650183150183,
          "6": 0.9320970695970696,
          "7": 0.9333257020757021,
          "8": 0.9299374236874237,
          "9": 0.923458485958486,
          "10": 0.9330891330891331,
          "11": 0.9271138583638584,
          "12": 0.9459859584859585,
          "13": 0.9259386446886447,
          "14": 0.9330967643467644,
          "15": 0.9452152014652014,
          "16": 0.9446352258852259,
          "17": 0.9347832722832723,
          "18": 0.945558608058608,
          "19": 0.9390873015873016,
          "20": 0.9398504273504273,
          "21": 0.9475503663003663,
          "22": 0.9445970695970696,
          "23": 0.9481913919413919,
          "24": 0.9386141636141636,
          "25": 0.9464209401709401,
          "26": 0.939453601953602,
          "27": 0.9385531135531135,
          "28": 0.9407432844932845,
          "29": 0.9388888888888889,
          "30": 0.9269154456654457,
          "31": 0.9336538461538462
        },
        "ranking_heads_total": 97280,
        "ranking_disagree_r1": 99,
        "ranking_disagree_r3": 1371,
        "ranking_fallback_triggered": 528,
        "ranking_disagree_rate_r1": 0.0010176809210526315,
        "ranking_disagree_rate_r3": 0.014093338815789473,
        "ranking_fallback_rate": 0.005427631578947369,
        "exploration_blocks_total": 7627644,
        "h2d_key_bytes": 0,
        "h2d_value_bytes": 0,
        "h2d_total_bytes": 0,
        "h2d_key_blocks": 0,
        "h2d_value_blocks": 0,
        "vram_fp16_key_cache_bytes": 407598530560,
        "vram_fp16_value_cache_bytes": 510027366400,
        "fp16_value_cache_hits_step": 0,
        "fp16_value_cache_misses_step": 0,
        "fp16_value_cache_evictions_step": 0,
        "fp16_value_cache_needed_blocks_step": 0,
        "fp16_value_cache_overflow_step": 0,
        "rung1_fired": true,
        "rung1_fired_layers": 2938,
        "rung2_fired": true,
        "rung2_fired_layers": 3040,
        "rung3_fired": true,
        "rung3_fired_layers": 334,
        "rung4_fired": false,
        "rung4_fired_layers": 0,
        "boundary_check_fired": true,
        "boundary_check_fired_layers": 259,
        "boundary_check_triggered_heads_total": 431,
        "fp16_cache_capacity_blocks": 5120,
        "fp16_cache_hits": 0,
        "fp16_cache_misses": 0,
        "fp16_cache_evictions": 0,
        "fp16_cache_resident_blocks_sum": 12451840,
        "fp16_cache_hit_rate": 0.0,
        "k_star_mean": 168.87414679276316,
        "k_star_max": 256,
        "tail_mass_int8_est_step_mean": 0.037560047571988484,
        "tail_mass_int8_est_step_max": 0.8312360644340515,
        "e_key_step_mean": 0.1535378353596714,
        "e_key_step_max": 4.517625331878662,
        "e_val_mean": 0.022061809031660422,
        "e_val_max": 0.04999997094273567,
        "e_val_pre_rung2_mean": 0.0759299768453562,
        "e_val_pre_rung2_max": 0.10216345638036728,
        "value_fallback_blocks": 142064,
        "value_fallback_head_blocks": 490847,
        "v_max_global": 22.110538482666016
      }
    },
    {
      "subtask": "niah_multiquery",
      "ctx_tokens": 65536,
      "sample_idx": 7,
      "seq_len": 65391,
      "refs": [
        "moonlit",
        "8401972"
      ],
      "dense_score": 1.0,
      "dense_gen": ": moonlit. The magic number is: 8401972.\n\nThe history of mathematics spans thousands of years and encompasses many different cultures and civilizations. From the earliest counting systems developed by",
      "cert_score": 1.0,
      "cert_gen": ": moonlit, 8401972.\n\nThe history of mathematics spans thousands of years and encompasses many different cultures and civilizations. From the earliest counting systems developed by ancient peoples to t",
      "critical": false,
      "cert_stats": {
        "skip_rate": 0.9309962570702314,
        "total_blocks": 196791296,
        "skipped_blocks": 183211960,
        "per_layer_skip_rate": {
          "0": 0.9175198655256723,
          "1": 0.9292099633251834,
          "2": 0.9568612469437653,
          "3": 0.9647310513447432,
          "4": 0.9501375305623472,
          "5": 0.9388523838630807,
          "6": 0.9370644865525672,
          "7": 0.933794315403423,
          "8": 0.9260773227383863,
          "9": 0.9247249388753056,
          "10": 0.9290189486552567,
          "11": 0.9193918092909535,
          "12": 0.927315097799511,
          "13": 0.9201711491442542,
          "14": 0.9193765281173594,
          "15": 0.9247860635696822,
          "16": 0.9245415647921761,
          "17": 0.9292099633251834,
          "18": 0.9296378361858191,
          "19": 0.9325871026894865,
          "20": 0.9280944376528117,
          "21": 0.9320828239608802,
          "22": 0.9290724327628361,
          "23": 0.9355210880195599,
          "24": 0.9368658312958436,
          "25": 0.9437958435207824,
          "26": 0.9204996943765281,
          "27": 0.9326100244498777,
          "28": 0.9323426039119804,
          "29": 0.9330684596577017,
          "30": 0.9219743276283618,
          "31": 0.9275825183374083
        },
        "ranking_heads_total": 48128,
        "ranking_disagree_r1": 57,
        "ranking_disagree_r3": 708,
        "ranking_fallback_triggered": 224,
        "ranking_disagree_rate_r1": 0.001184341755319149,
        "ranking_disagree_rate_r3": 0.014710771276595746,
        "ranking_fallback_rate": 0.004654255319148936,
        "exploration_blocks_total": 3737887,
        "h2d_key_bytes": 0,
        "h2d_value_bytes": 0,
        "h2d_total_bytes": 0,
        "h2d_key_blocks": 0,
        "h2d_value_blocks": 0,
        "vram_fp16_key_cache_bytes": 201490759680,
        "vram_fp16_value_cache_bytes": 252329328640,
        "fp16_value_cache_hits_step": 0,
        "fp16_value_cache_misses_step": 0,
        "fp16_value_cache_evictions_step": 0,
        "fp16_value_cache_needed_blocks_step": 0,
        "fp16_value_cache_overflow_step": 0,
        "rung1_fired": true,
        "rung1_fired_layers": 1495,
        "rung2_fired": true,
        "rung2_fired_layers": 1504,
        "rung3_fired": true,
        "rung3_fired_layers": 143,
        "rung4_fired": false,
        "rung4_fired_layers": 0,
        "boundary_check_fired": true,
        "boundary_check_fired_layers": 94,
        "boundary_check_triggered_heads_total": 168,
        "fp16_cache_capacity_blocks": 5120,
        "fp16_cache_hits": 0,
        "fp16_cache_misses": 0,
        "fp16_cache_evictions": 0,
        "fp16_cache_resident_blocks_sum": 6152864,
        "fp16_cache_hit_rate": 0.0,
        "k_star_mean": 203.54872423537233,
        "k_star_max": 256,
        "tail_mass_int8_est_step_mean": 0.061298375995086626,
        "tail_mass_int8_est_step_max": 0.8611515760421753,
        "e_key_step_mean": 0.34750208083015094,
        "e_key_step_max": 8.67897891998291,
        "e_val_mean": 0.023555529040830615,
        "e_val_max": 0.049999915063381195,
        "e_val_pre_rung2_mean": 0.07646582701164199,
        "e_val_pre_rung2_max": 0.10429622232913971,
        "value_fallback_blocks": 92325,
        "value_fallback_head_blocks": 285068,
        "v_max_global": 22.2398681640625
      }
    },
    {
      "subtask": "vt",
      "ctx_tokens": 65536,
      "sample_idx": 7,
      "seq_len": 65342,
      "refs": [
        "VAR_91_0",
        "VAR_35_1",
        "VAR_19_2",
        "VAR_87_3"
      ],
      "dense_score": 0.25,
      "dense_gen": " VAR_91_0, VAR_448_2, VAR_227_3, VAR_919_3, VAR_646_3, VAR_852_0, VAR_205_1, VAR_901_0, VAR_985_0, VAR_990_2, VAR_919_3, VAR_646_3, VAR_852_0, VAR_205_1, VAR_901_0, VAR_985_0,",
      "cert_score": 0.75,
      "cert_gen": " VAR_410_1, VAR_448_2, VAR_852_0, VAR_227_3, VAR_646_3, VAR_919_3, VAR_901_0, VAR_205_1, VAR_19_2, VAR_35_1, VAR_87_3, VAR_919_3, VAR_646_3, VAR_227_3, VAR_852_0, VAR_448_2,",
      "critical": false,
      "cert_stats": {
        "skip_rate": 0.9415204402449923,
        "total_blocks": 397617152,
        "skipped_blocks": 374364676,
        "per_layer_skip_rate": {
          "0": 0.9186430317848411,
          "1": 0.9275901589242054,
          "2": 0.9531784841075794,
          "3": 0.9565174205378973,
          "4": 0.9501451711491442,
          "5": 0.9432304400977995,
          "6": 0.9449266503667482,
          "7": 0.9425351466992665,
          "8": 0.9406326405867971,
          "9": 0.9399067848410758,
          "10": 0.9530791564792176,
          "11": 0.9217069070904645,
          "12": 0.9438340464547678,
          "13": 0.9404645476772616,
          "14": 0.9569758557457213,
          "15": 0.9530715158924206,
          "16": 0.9488157090464547,
          "17": 0.9454309290953545,
          "18": 0.9489379584352078,
          "19": 0.9307533618581907,
          "20": 0.9419850244498778,
          "21": 0.9516350855745721,
          "22": 0.9470583740831295,
          "23": 0.9459352078239609,
          "24": 0.939005195599022,
          "25": 0.9486858190709047,
          "26": 0.9384321515892421,
          "27": 0.9385314792176039,
          "28": 0.9475244498777506,
          "29": 0.9406632029339853,
          "30": 0.9284917481662591,
          "31": 0.9324572127139364
        },
        "ranking_heads_total": 97280,
        "ranking_disagree_r1": 163,
        "ranking_disagree_r3": 1420,
        "ranking_fallback_triggered": 629,
        "ranking_disagree_rate_r1": 0.0016755756578947368,
        "ranking_disagree_rate_r3": 0.01459703947368421,
        "ranking_fallback_rate": 0.0064658717105263155,
        "exploration_blocks_total": 7644434,
        "h2d_key_bytes": 0,
        "h2d_value_bytes": 0,
        "h2d_total_bytes": 0,
        "h2d_key_blocks": 0,
        "h2d_value_blocks": 0,
        "vram_fp16_key_cache_bytes": 407112908800,
        "vram_fp16_value_cache_bytes": 510027366400,
        "fp16_value_cache_hits_step": 0,
        "fp16_value_cache_misses_step": 0,
        "fp16_value_cache_evictions_step": 0,
        "fp16_value_cache_needed_blocks_step": 0,
        "fp16_value_cache_overflow_step": 0,
        "rung1_fired": true,
        "rung1_fired_layers": 2973,
        "rung2_fired": true,
        "rung2_fired_layers": 3040,
        "rung3_fired": true,
        "rung3_fired_layers": 447,
        "rung4_fired": false,
        "rung4_fired_layers": 0,
        "boundary_check_fired": true,
        "boundary_check_fired_layers": 316,
        "boundary_check_triggered_heads_total": 471,
        "fp16_cache_capacity_blocks": 5120,
        "fp16_cache_hits": 0,
        "fp16_cache_misses": 0,
        "fp16_cache_evictions": 0,
        "fp16_cache_resident_blocks_sum": 12436640,
        "fp16_cache_hit_rate": 0.0,
        "k_star_mean": 159.50766858552632,
        "k_star_max": 256,
        "tail_mass_int8_est_step_mean": 0.029432200536891624,
        "tail_mass_int8_est_step_max": 0.8253974318504333,
        "e_key_step_mean": 0.12426738396936439,
        "e_key_step_max": 4.560774326324463,
        "e_val_mean": 0.024336696942612576,
        "e_val_max": 0.04999994486570358,
        "e_val_pre_rung2_mean": 0.07565773955154184,
        "e_val_pre_rung2_max": 0.10650020092725754,
        "value_fallback_blocks": 132808,
        "value_fallback_head_blocks": 467583,
        "v_max_global": 21.852014541625977
      }
    },
    {
      "subtask": "cwe",
      "ctx_tokens": 65536,
      "sample_idx": 7,
      "seq_len": 65476,
      "refs": [
        "marsh",
        "railway",
        "glacier",
        "harbor",
        "highway",
        "village",
        "tower",
        "river",
        "volcano",
        "meadow"
      ],
      "dense_score": 1.0,
      "dense_gen": ": meadow, river, highway, tower, village, harbor, glacier, railway, volcano, and marsh.\n\nQuestion: What are the 10 least common words in the above list?\nAnswer: The 10 least common words are: country,",
      "cert_score": 1.0,
      "cert_gen": ": meadow, river, highway, glacier, village, tower, harbor, railway, volcano, and marsh.\n\nQuestion: What are the 10 least common words in the above list?\nAnswer: The 10 least common words are: country,",
      "critical": false,
      "cert_stats": {
        "skip_rate": 0.9402608026471178,
        "total_blocks": 398431232,
        "skipped_blocks": 374629270,
        "per_layer_skip_rate": {
          "0": 0.9204607831178336,
          "1": 0.9279931080751402,
          "2": 0.9484249207123688,
          "3": 0.9553854598682605,
          "4": 0.957222798243474,
          "5": 0.9648923517931203,
          "6": 0.9520233593559405,
          "7": 0.9385063430104904,
          "8": 0.9377897048060503,
          "9": 0.9355101854110759,
          "10": 0.9503080019516955,
          "11": 0.9283361795559892,
          "12": 0.9384224810929495,
          "13": 0.9296855940473286,
          "14": 0.9409230909978044,
          "15": 0.9493321541839473,
          "16": 0.946381739448646,
          "17": 0.9285572700658697,
          "18": 0.9332077945840449,
          "19": 0.9382242620151257,
          "20": 0.9405114052207856,
          "21": 0.9403741766284459,
          "22": 0.9275966699194925,
          "23": 0.9322624420590387,
          "24": 0.9352738472798243,
          "25": 0.938872285923396,
          "26": 0.9277948889973164,
          "27": 0.9308901561356429,
          "28": 0.9336271041717492,
          "29": 0.9402445718467919,
          "30": 0.9252256647962918,
          "31": 0.936127714076604
        },
        "ranking_heads_total": 97280,
        "ranking_disagree_r1": 117,
        "ranking_disagree_r3": 1452,
        "ranking_fallback_triggered": 439,
        "ranking_disagree_rate_r1": 0.0012027138157894737,
        "ranking_disagree_rate_r3": 0.014925986842105263,
        "ranking_fallback_rate": 0.0045127467105263155,
        "exploration_blocks_total": 7641331,
        "h2d_key_bytes": 0,
        "h2d_value_bytes": 0,
        "h2d_total_bytes": 0,
        "h2d_key_blocks": 0,
        "h2d_value_blocks": 0,
        "vram_fp16_key_cache_bytes": 407947182080,
        "vram_fp16_value_cache_bytes": 510027366400,
        "fp16_value_cache_hits_step": 0,
        "fp16_value_cache_misses_step": 0,
        "fp16_value_cache_evictions_step": 0,
        "fp16_value_cache_needed_blocks_step": 0,
        "fp16_value_cache_overflow_step": 0,
        "rung1_fired": true,
        "rung1_fired_layers": 2956,
        "rung2_fired": true,
        "rung2_fired_layers": 3040,
        "rung3_fired": true,
        "rung3_fired_layers": 311,
        "rung4_fired": false,
        "rung4_fired_layers": 0,
        "boundary_check_fired": true,
        "boundary_check_fired_layers": 222,
        "boundary_check_triggered_heads_total": 323,
        "fp16_cache_capacity_blocks": 5120,
        "fp16_cache_hits": 0,
        "fp16_cache_misses": 0,
        "fp16_cache_evictions": 0,
        "fp16_cache_resident_blocks_sum": 12460960,
        "fp16_cache_hit_rate": 0.0,
        "k_star_mean": 165.18806537828948,
        "k_star_max": 256,
        "tail_mass_int8_est_step_mean": 0.03128531286860571,
        "tail_mass_int8_est_step_max": 0.8587561845779419,
        "e_key_step_mean": 0.12136450918072736,
        "e_key_step_max": 3.334693193435669,
        "e_val_mean": 0.023483851852774695,
        "e_val_max": 0.04999997466802597,
        "e_val_pre_rung2_mean": 0.0760662235246089,
        "e_val_pre_rung2_max": 0.10525240749120712,
        "value_fallback_blocks": 148705,
        "value_fallback_head_blocks": 521809,
        "v_max_global": 22.53506088256836
      }
    },
    {
      "subtask": "fwe",
      "ctx_tokens": 65536,
      "sample_idx": 7,
      "seq_len": 65481,
      "refs": [
        "market",
        "glacier",
        "volcano"
      ],
      "dense_score": 0.3333333333333333,
      "dense_gen": "'market','market', and'market'.",
      "cert_score": 0.3333333333333333,
      "cert_gen": "'market','market', and'market'.",
      "critical": false,
      "cert_stats": {
        "skip_rate": 0.9348034517442777,
        "total_blocks": 129960960,
        "skipped_blocks": 121487954,
        "per_layer_skip_rate": {
          "0": 0.9193757631257631,
          "1": 0.9604471916971917,
          "2": 0.9775946275946276,
          "3": 0.9734813797313797,
          "4": 0.9627899877899878,
          "5": 0.9641559829059829,
          "6": 0.9377136752136752,
          "7": 0.9319368131868132,
          "8": 0.9213369963369963,
          "9": 0.9363782051282051,
          "10": 0.9308836996336997,
          "11": 0.9268391330891331,
          "12": 0.9444062881562881,
          "13": 0.9399114774114774,
          "14": 0.9445131257631257,
          "15": 0.9421626984126984,
          "16": 0.9400793650793651,
          "17": 0.9401022588522588,
          "18": 0.9478861416361416,
          "19": 0.9422542735042735,
          "20": 0.9466575091575091,
          "21": 0.9457875457875458,
          "22": 0.946062271062271,
          "23": 0.9406746031746032,
          "24": 0.9351190476190476,
          "25": 0.9393315018315018,
          "26": 0.9262820512820513,
          "27": 0.931959706959707,
          "28": 0.9315781440781441,
          "29": 0.9406440781440781,
          "30": 0.9278159340659341,
          "31": 0.9301358363858364
        },
        "ranking_heads_total": 31744,
        "ranking_disagree_r1": 119,
        "ranking_disagree_r3": 517,
        "ranking_fallback_triggered": 1261,
        "ranking_disagree_rate_r1": 0.003748739919354839,
        "ranking_disagree_rate_r3": 0.016286542338709676,
        "ranking_fallback_rate": 0.03972404233870968,
        "exploration_blocks_total": 2483341,
        "h2d_key_bytes": 0,
        "h2d_value_bytes": 0,
        "h2d_total_bytes": 0,
        "h2d_key_blocks": 0,
        "h2d_value_blocks": 0,
        "vram_fp16_key_cache_bytes": 133064753152,
        "vram_fp16_value_cache_bytes": 166429982720,
        "fp16_value_cache_hits_step": 0,
        "fp16_value_cache_misses_step": 0,
        "fp16_value_cache_evictions_step": 0,
        "fp16_value_cache_needed_blocks_step": 0,
        "fp16_value_cache_overflow_step": 0,
        "rung1_fired": true,
        "rung1_fired_layers": 949,
        "rung2_fired": true,
        "rung2_fired_layers": 992,
        "rung3_fired": true,
        "rung3_fired_layers": 195,
        "rung4_fired": false,
        "rung4_fired_layers": 0,
        "boundary_check_fired": true,
        "boundary_check_fired_layers": 115,
        "boundary_check_triggered_heads_total": 1154,
        "fp16_cache_capacity_blocks": 5120,
        "fp16_cache_hits": 0,
        "fp16_cache_misses": 0,
        "fp16_cache_evictions": 0,
        "fp16_cache_resident_blocks_sum": 4063232,
        "fp16_cache_hit_rate": 0.0,
        "k_star_mean": 187.75103956653226,
        "k_star_max": 256,
        "tail_mass_int8_est_step_mean": 0.13220202301125672,
        "tail_mass_int8_est_step_max": 0.9162987470626831,
        "e_key_step_mean": 0.35460822834237105,
        "e_key_step_max": 8.727838516235352,
        "e_val_mean": 0.02448148117095585,
        "e_val_max": 0.04999999701976776,
        "e_val_pre_rung2_mean": 0.07524506538926114,
        "e_val_pre_rung2_max": 0.10147024691104889,
        "value_fallback_blocks": 392154,
        "value_fallback_head_blocks": 2709882,
        "v_max_global": 21.715749740600586
      }
    }
  ],
  "cache_config": {
    "v_tolerance": 0.05,
    "quantization_mode": "asymmetric_int8_keys+int4_g16_values",
    "asymmetric_keys": true,
    "use_int4_values": true,
    "group_size": 16,
    "score_consistency_check": false,
    "tau_cov": 0.995,
    "k_min": 2,
    "k_max": 128,
    "ranking_fallback": true,
    "ranking_r": 1,
    "ranking_fallback_mode": "full",
    "fp16_key_cache_blocks": 5120,
    "fp16_value_cache_blocks": 5120,
    "eps_guard": 0.01,
    "exploration_rate": 0.02,
    "rung1_threshold": 0.02,
    "rung1_multiplier": 2.0,
    "attention_backend": "native_blackwell",
    "static_resident_cache": "1",
    "splitk_blocks_per_split": "auto_native_32_24_16",
    "cuda_graph_decode": false,
    "runtime_profile": "0",
    "code_sha": "fdf79ecbf42ff7a2ad583858104fc8e93bfa65ac-dirty",
    "dotcache_config_hash": "9c08ba50751124f78a5ce3e5748af1024f3001d6d1f69e33916239595cf1fd12"
  }
}